[
  {
    "question": "LAR vs. Panthers",
    "date": "2025-11-30",
    "slug": "nfl-la-car-2025-11-30",
    "LAR BUY": 0.84,
    "Panthers BUY": null
  },
  {
    "question": "49ers vs. Browns",
    "date": "2025-11-30",
    "slug": "nfl-sf-cle-2025-11-30",
    "49ers BUY": null,
    "Browns BUY": 0.31
  },
  {
    "question": "Texans vs. Colts",
    "date": "2025-11-30",
    "slug": "nfl-hou-ind-2025-11-30",
    "Texans BUY": 0.39,
    "Colts BUY": 0.62
  },
  {
    "question": "Saints vs. Dolphins",
    "date": "2025-11-30",
    "slug": "nfl-no-mia-2025-11-30",
    "Saints BUY": 0.3,
    "Dolphins BUY": 0.71
  },
  {
    "question": "Falcons vs. Jets",
    "date": "2025-11-30",
    "slug": "nfl-atl-nyj-2025-11-30",
    "Falcons BUY": 0.62,
    "Jets BUY": 0.39
  },
  {
    "question": "Cardinals vs. Buccaneers",
    "date": "2025-11-30",
    "slug": "nfl-ari-tb-2025-11-30",
    "Cardinals BUY": 0.36,
    "Buccaneers BUY": 0.65
  },
  {
    "question": "Jaguars vs. Titans",
    "date": "2025-11-30",
    "slug": "nfl-jax-ten-2025-11-30",
    "Jaguars BUY": 0.72,
    "Titans BUY": 0.29
  },
  {
    "question": "Vikings vs. Seahawks",
    "date": "2025-11-30",
    "slug": "nfl-min-sea-2025-11-30",
    "Vikings BUY": 0.14,
    "Seahawks BUY": 0.87
  },
  {
    "question": "Raiders vs. Chargers",
    "date": "2025-11-30",
    "slug": "nfl-lv-lac-2025-11-30",
    "Raiders BUY": 0.18,
    "Chargers BUY": 0.83
  },
  {
    "question": "Bills vs. Steelers",
    "date": "2025-11-30",
    "slug": "nfl-buf-pit-2025-11-30",
    "Bills BUY": 0.62,
    "Steelers BUY": 0.39
  },
  {
    "question": "Broncos vs. Commanders",
    "date": "2025-11-30",
    "slug": "nfl-den-was-2025-11-30",
    "Broncos BUY": 0.74,
    "Commanders BUY": 0.27
  },
  {
    "question": "Giants vs. Patriots",
    "date": "2025-12-01",
    "slug": "nfl-nyg-ne-2025-12-01",
    "Giants BUY": 0.24,
    "Patriots BUY": 0.77
  },
  {
    "question": "Cowboys vs. Lions",
    "date": "2025-12-04",
    "slug": "nfl-dal-det-2025-12-04",
    "Cowboys BUY": 0.4,
    "Lions BUY": 0.63
  },
  {
    "question": "Seahawks vs. Falcons",
    "date": "2025-12-07",
    "slug": "nfl-sea-atl-2025-12-07",
    "Seahawks BUY": 0.8,
    "Falcons BUY": 0.24
  },
  {
    "question": "Steelers vs. Ravens",
    "date": "2025-12-07",
    "slug": "nfl-pit-bal-2025-12-07",
    "Steelers BUY": 0.32,
    "Ravens BUY": 0.75
  },
  {
    "question": "Titans vs. Browns",
    "date": "2025-12-07",
    "slug": "nfl-ten-cle-2025-12-07",
    "Titans BUY": 0.37,
    "Browns BUY": 0.68
  },
  {
    "question": "Bears vs. Packers",
    "date": "2025-12-07",
    "slug": "nfl-chi-gb-2025-12-07",
    "Bears BUY": 0.33,
    "Packers BUY": 0.7
  },
  {
    "question": "Colts vs. Jaguars",
    "date": "2025-12-07",
    "slug": "nfl-ind-jax-2025-12-07",
    "Colts BUY": 0.63,
    "Jaguars BUY": 0.43
  },
  {
    "question": "Commanders vs. Vikings",
    "date": "2025-12-07",
    "slug": "nfl-was-min-2025-12-07",
    "Commanders BUY": 0.48,
    "Vikings BUY": 0.57
  },
  {
    "question": "Dolphins vs. Jets",
    "date": "2025-12-07",
    "slug": "nfl-mia-nyj-2025-12-07",
    "Dolphins BUY": 0.62,
    "Jets BUY": 0.46
  },
  {
    "question": "Saints vs. Buccaneers",
    "date": "2025-12-07",
    "slug": "nfl-no-tb-2025-12-07",
    "Saints BUY": 0.24,
    "Buccaneers BUY": 0.8
  },
  {
    "question": "Broncos vs. Raiders",
    "date": "2025-12-07",
    "slug": "nfl-den-lv-2025-12-07",
    "Broncos BUY": 0.83,
    "Raiders BUY": 0.24
  },
  {
    "question": "LAR vs. Cardinals",
    "date": "2025-12-07",
    "slug": "nfl-lar-ari-2025-12-07",
    "LAR BUY": 0.92,
    "Cardinals BUY": 0.42
  },
  {
    "question": "Bengals vs. Bills",
    "date": "2025-12-07",
    "slug": "nfl-cin-buf-2025-12-07",
    "Bengals BUY": 0.29,
    "Bills BUY": 0.76
  },
  {
    "question": "Texans vs. Chiefs",
    "date": "2025-12-07",
    "slug": "nfl-hou-kc-2025-12-07",
    "Texans BUY": 0.37,
    "Chiefs BUY": 0.69
  },
  {
    "question": "Eagles vs. Chargers",
    "date": "2025-12-08",
    "slug": "nfl-phi-lac-2025-12-08",
    "Eagles BUY": 0.8,
    "Chargers BUY": 0.59
  },
  {
    "question": "Falcons vs. Buccaneers",
    "date": "2025-12-11",
    "slug": "nfl-atl-tb-2025-12-11",
    "Falcons BUY": 0.97,
    "Buccaneers BUY": 0.97
  }
]